<annotation>
	<folder>train</folder>
	<filename>orange_69.jpg</filename>
	<path>C:\tensorflow1\models\research\object_detection\images\train\orange_69.jpg</path>
	<source>
		<database>Unknown</database>
	</source>
	<size>
		<width>1024</width>
		<height>640</height>
		<depth>3</depth>
	</size>
	<segmented>0</segmented>
	<object>
		<name>orange</name>
		<pose>Unspecified</pose>
		<truncated>0</truncated>
		<difficult>0</difficult>
		<bndbox>
			<xmin>27</xmin>
			<ymin>247</ymin>
			<xmax>291</xmax>
			<ymax>499</ymax>
		</bndbox>
	</object>
	<object>
		<name>orange</name>
		<pose>Unspecified</pose>
		<truncated>0</truncated>
		<difficult>0</difficult>
		<bndbox>
			<xmin>733</xmin>
			<ymin>268</ymin>
			<xmax>1004</xmax>
			<ymax>535</ymax>
		</bndbox>
	</object>
	<object>
		<name>orange</name>
		<pose>Unspecified</pose>
		<truncated>0</truncated>
		<difficult>0</difficult>
		<bndbox>
			<xmin>543</xmin>
			<ymin>213</ymin>
			<xmax>796</xmax>
			<ymax>440</ymax>
		</bndbox>
	</object>
	<object>
		<name>orange</name>
		<pose>Unspecified</pose>
		<truncated>0</truncated>
		<difficult>0</difficult>
		<bndbox>
			<xmin>283</xmin>
			<ymin>247</ymin>
			<xmax>517</xmax>
			<ymax>455</ymax>
		</bndbox>
	</object>
</annotation>
